PC_ROM/instr_mem.sv
module instr_mem #(
    parameter   ADDRESS_WIDTH = 32,
                DATAOUT_WIDTH = 32,
                DATA_WIDTH = 8
)(
    input logic [ADDRESS_WIDTH-1:0] A,
    output logic [DATAOUT_WIDTH-1:0] RD
);

logic [DATA_WIDTH-1:0] rom_array [20:0]; // the parameter after the rom_array is the size of the .mem file

initial begin
        $display("Loading rom.");
        $readmemh("test1.mem", rom_array);
end;

assign RD = {rom_array [A],rom_array [A+1],rom_array [A+2],rom_array [A+3]};

endmodule

PC_ROM/blue_part.sv
module blue_part #(
    parameter address_width = 8
)(
    input logic                            PCsrc, // output from control unit
    input logic                            clk,
    input logic                            rst,
    input logic [address_width-1:0]        ImmOp, // output from "sign extend" block
    output logic [address_width-1:0]       PC
);

//logic       next_pc;

always_ff@(posedge clk) begin
    if (rst)        PC <= {address_width{1'b0}};
    else if (PCsrc)      PC <= PC + ImmOp;
    else            PC <= PC + 4;
end

endmodule

PC_ROM/top.sv
module top#(
    parameter ADDRESS_WIDTH = 32,
    DATAOUT_WIDTH = 32
)(
    input logic                            PCsrc, // output from control unit
    input logic                            clk,
    input logic                            rst,
    input logic [ADDRESS_WIDTH-1:0]        ImmOp, // output from "sign extend" block
  //  output logic [ADDRESS_WIDTH-1:0]       PC,
  //  input logic [ADDRESS_WIDTH-1:0]        A,
    output logic [DATAOUT_WIDTH-1:0]       RD
);

logic [ADDRESS_WIDTH-1:0]        A;

blue_part pc(
    .PCsrc(PCsrc),
    .clk(clk),
    .rst(rst),
    .ImmOp(ImmOp),
    .PC(A)
);

instr_mem mem(
    .A(A),
    .RD(RD)
);

endmodule

PC_ROM/top.vcd
$version Generated by VerilatedVcd $end
$date Sun Nov 20 16:51:15 2022 $end
$timescale 1ps $end

 $scope module TOP $end
  $var wire 32 ; ImmOp [31:0] $end
  $var wire  1 8 PCsrc $end
  $var wire 32 < RD [31:0] $end
  $var wire  1 9 clk $end
  $var wire  1 : rst $end
  $scope module top $end
   $var wire 32 = A [31:0] $end
   $var wire 32 > ADDRESS_WIDTH [31:0] $end
   $var wire 32 > DATAOUT_WIDTH [31:0] $end
   $var wire 32 ; ImmOp [31:0] $end
   $var wire  1 8 PCsrc $end
   $var wire 32 < RD [31:0] $end
   $var wire  1 9 clk $end
   $var wire  1 : rst $end
   $scope module mem $end
    $var wire 32 = A [31:0] $end
    $var wire 32 > ADDRESS_WIDTH [31:0] $end
    $var wire 32 > DATAOUT_WIDTH [31:0] $end
    $var wire 32 ? DATA_WIDTH [31:0] $end
    $var wire 32 < RD [31:0] $end
    $var wire  8 # rom_array[0] [7:0] $end
    $var wire  8 - rom_array[10] [7:0] $end
    $var wire  8 . rom_array[11] [7:0] $end
    $var wire  8 / rom_array[12] [7:0] $end
    $var wire  8 0 rom_array[13] [7:0] $end
    $var wire  8 1 rom_array[14] [7:0] $end
    $var wire  8 2 rom_array[15] [7:0] $end
    $var wire  8 3 rom_array[16] [7:0] $end
    $var wire  8 4 rom_array[17] [7:0] $end
    $var wire  8 5 rom_array[18] [7:0] $end
    $var wire  8 6 rom_array[19] [7:0] $end
    $var wire  8 $ rom_array[1] [7:0] $end
    $var wire  8 7 rom_array[20] [7:0] $end
    $var wire  8 % rom_array[2] [7:0] $end
    $var wire  8 & rom_array[3] [7:0] $end
    $var wire  8 ' rom_array[4] [7:0] $end
    $var wire  8 ( rom_array[5] [7:0] $end
    $var wire  8 ) rom_array[6] [7:0] $end
    $var wire  8 * rom_array[7] [7:0] $end
    $var wire  8 + rom_array[8] [7:0] $end
    $var wire  8 , rom_array[9] [7:0] $end
   $upscope $end
   $scope module pc $end
    $var wire 32 ; ImmOp [31:0] $end
    $var wire 32 = PC [31:0] $end
    $var wire  1 8 PCsrc $end
    $var wire 32 > address_width [31:0] $end
    $var wire  1 9 clk $end
    $var wire  1 : rst $end
   $upscope $end
  $upscope $end
 $upscope $end
$enddefinitions $end


#0
b00000000 #
b00000000 $
b00000000 %
b00000000 &
b00000000 '
b00000000 (
b00000000 )
b00000000 *
b00000000 +
b00000000 ,
b00000000 -
b00000000 .
b00000000 /
b00000000 0
b00000000 1
b00000000 2
b00000000 3
b00000000 4
b00000000 5
b00000000 6
b00000000 7
08
19
0:
b00000000000000000000000000001000 ;
b00000000000000000000000000000000 <
b00000000000000000000000000000000 =
b00000000000000000000000000100000 >
b00000000000000000000000000001000 ?
#1
b00000001 $
b00000010 %
b00000011 &
b00000100 '
b00000101 (
b00000110 )
b00000111 *
b00001000 +
b00001001 ,
b00001010 -
b00001011 .
b00001100 /
b00001101 0
b00001110 1
b00001111 2
b00010000 3
b00010001 4
b00010010 5
b00010011 6
09
b00000000000000010000001000000011 <
#2
19
b00000100000001010000011000000111 <
b00000000000000000000000000000100 =
#3
09
#4
19
b00001000000010010000101000001011 <
b00000000000000000000000000001000 =
#5
09
#6
19
b00001100000011010000111000001111 <
b00000000000000000000000000001100 =
#7
09
#8
19
b00010000000100010001001000010011 <
b00000000000000000000000000010000 =
#9
09
#10
19
b00000000000000000000000000000000 <
b00000000000000000000000000010100 =
#11
09
#12
19
b00000000000000000000000000011000 =
#13
09
#14
19
b00000000000000000000000000011100 =
#15
09
#16
19
b00000000000000010000001000000011 <
b00000000000000000000000000100000 =
#17
09
#18
19
b00000100000001010000011000000111 <
b00000000000000000000000000100100 =
#19
09
#20
19
b00001000000010010000101000001011 <
b00000000000000000000000000101000 =
#21
09
#22
18
19
b00001100000011010000111000001111 <
b00000000000000000000000000101100 =
#23
09
#24
08
19
b00000000000000000000000000000000 <
b00000000000000000000000000110100 =
#25
09
#26
19
b00000000000000000000000000111000 =
#27
09
#28
19
b00000000000000000000000000111100 =
#29
09
#30
19
b00000000000000010000001000000011 <
b00000000000000000000000001000000 =
#31
09
#32
19
b00000100000001010000011000000111 <
b00000000000000000000000001000100 =
#33
09
#34
19
b00001000000010010000101000001011 <
b00000000000000000000000001001000 =
#35
09
#36
19
b00001100000011010000111000001111 <
b00000000000000000000000001001100 =
#37
09
#38
19
b00010000000100010001001000010011 <
b00000000000000000000000001010000 =
#39
09
#40
19
b00000000000000000000000000000000 <
b00000000000000000000000001010100 =
#41
09
#42
19
1:
b00000000000000000000000001011000 =
#43
09
#44
19
0:
b00000000000000010000001000000011 <
b00000000000000000000000000000000 =
#45
09
#46
19
b00000100000001010000011000000111 <
b00000000000000000000000000000100 =
#47
09
#48
19
b00001000000010010000101000001011 <
b00000000000000000000000000001000 =
#49
09
#50
19
b00001100000011010000111000001111 <
b00000000000000000000000000001100 =
#51
09
#52
19
b00010000000100010001001000010011 <
b00000000000000000000000000010000 =
#53
09
#54
19
b00000000000000000000000000000000 <
b00000000000000000000000000010100 =
#55
09
#56
19
b00000000000000000000000000011000 =
#57
09
#58
19
b00000000000000000000000000011100 =
#59
09
#60
19
b00000000000000010000001000000011 <
b00000000000000000000000000100000 =
#61
09
#62
19
b00000100000001010000011000000111 <
b00000000000000000000000000100100 =
#63
09
#64
19
b00001000000010010000101000001011 <
b00000000000000000000000000101000 =
#65
09
#66
19
b00001100000011010000111000001111 <
b00000000000000000000000000101100 =
#67
09
#68
19
b00010000000100010001001000010011 <
b00000000000000000000000000110000 =
#69
09
#70
19
b00000000000000000000000000000000 <
b00000000000000000000000000110100 =
#71
09
#72
19
b00000000000000000000000000111000 =
#73
09
#74
19
b00000000000000000000000000111100 =
#75
09
#76
19
b00000000000000010000001000000011 <
b00000000000000000000000001000000 =
#77
09
#78
19
b00000100000001010000011000000111 <
b00000000000000000000000001000100 =
#79
09
#80
19
b00001000000010010000101000001011 <
b00000000000000000000000001001000 =
#81
09
#82
19
b00001100000011010000111000001111 <
b00000000000000000000000001001100 =
#83
09
#84
19
b00010000000100010001001000010011 <
b00000000000000000000000001010000 =
#85
09
#86
19
b00000000000000000000000000000000 <
b00000000000000000000000001010100 =
#87
09
#88
19
b00000000000000000000000001011000 =
#89
09
#90
19
b00000000000000000000000001011100 =
#91
09
#92
19
b00000000000000010000001000000011 <
b00000000000000000000000001100000 =
#93
09
#94
19
b00000100000001010000011000000111 <
b00000000000000000000000001100100 =
#95
09
#96
19
b00001000000010010000101000001011 <
b00000000000000000000000001101000 =
#97
09
#98
19
b00001100000011010000111000001111 <
b00000000000000000000000001101100 =
#99
09
#100
19
b00010000000100010001001000010011 <
b00000000000000000000000001110000 =
#101
09
#102
19
b00000000000000000000000000000000 <
b00000000000000000000000001110100 =
#103
09
#104
19
b00000000000000000000000001111000 =
#105
09
#106
19
b00000000000000000000000001111100 =
#107
09
#108
19
b00000000000000010000001000000011 <
b00000000000000000000000010000000 =
#109
09
#110
19
b00000100000001010000011000000111 <
b00000000000000000000000010000100 =
#111
09
#112
19
b00001000000010010000101000001011 <
b00000000000000000000000010001000 =
#113
09
#114
19
b00001100000011010000111000001111 <
b00000000000000000000000010001100 =
#115
09
#116
19
b00010000000100010001001000010011 <
b00000000000000000000000010010000 =
#117
09
#118
19
b00000000000000000000000000000000 <
b00000000000000000000000010010100 =
#119
09
#120
19
b00000000000000000000000010011000 =
#121
09
#122
19
b00000000000000000000000010011100 =
#123
09
#124
19
b00000000000000010000001000000011 <
b00000000000000000000000010100000 =
#125
09
#126
19
b00000100000001010000011000000111 <
b00000000000000000000000010100100 =
#127
09
#128
19
b00001000000010010000101000001011 <
b00000000000000000000000010101000 =
#129
09
#130
19
b00001100000011010000111000001111 <
b00000000000000000000000010101100 =
#131
09
#132
19
b00010000000100010001001000010011 <
b00000000000000000000000010110000 =
#133
09
#134
19
b00000000000000000000000000000000 <
b00000000000000000000000010110100 =
#135
09
#136
19
b00000000000000000000000010111000 =
#137
09
#138
19
b00000000000000000000000010111100 =
#139
09
#140
19
b00000000000000010000001000000011 <
b00000000000000000000000011000000 =
#141
09
#142
19
b00000100000001010000011000000111 <
b00000000000000000000000011000100 =
#143
09
#144
19
b00001000000010010000101000001011 <
b00000000000000000000000011001000 =
#145
09
#146
19
b00001100000011010000111000001111 <
b00000000000000000000000011001100 =
#147
09
#148
19
b00010000000100010001001000010011 <
b00000000000000000000000011010000 =
#149
09
#150
19
b00000000000000000000000000000000 <
b00000000000000000000000011010100 =
#151
09
#152
19
b00000000000000000000000011011000 =
#153
09
#154
19
b00000000000000000000000011011100 =
#155
09
#156
19
b00000000000000010000001000000011 <
b00000000000000000000000011100000 =
#157
09
#158
19
b00000100000001010000011000000111 <
b00000000000000000000000011100100 =
#159
09
#160
19
b00001000000010010000101000001011 <
b00000000000000000000000011101000 =
#161
09
#162
19
b00001100000011010000111000001111 <
b00000000000000000000000011101100 =
#163
09
#164
19
b00010000000100010001001000010011 <
b00000000000000000000000011110000 =
#165
09
#166
19
b00000000000000000000000000000000 <
b00000000000000000000000011110100 =
#167
09
#168
19
b00000000000000000000000011111000 =
#169
09
#170
19
b00000000000000000000000011111100 =
#171
09
#172
19
b00000000000000010000001000000011 <
b00000000000000000000000100000000 =
#173
09
#174
19
b00000100000001010000011000000111 <
b00000000000000000000000100000100 =
#175
09
#176
19
b00001000000010010000101000001011 <
b00000000000000000000000100001000 =
#177
09
#178
19
b00001100000011010000111000001111 <
b00000000000000000000000100001100 =
#179
09
#180
19
b00010000000100010001001000010011 <
b00000000000000000000000100010000 =
#181
09
#182
19
b00000000000000000000000000000000 <
b00000000000000000000000100010100 =
#183
09
#184
19
b00000000000000000000000100011000 =
#185
09
#186
19
b00000000000000000000000100011100 =
#187
09
#188
19
b00000000000000010000001000000011 <
b00000000000000000000000100100000 =
#189
09
#190
19
b00000100000001010000011000000111 <
b00000000000000000000000100100100 =
#191
09
#192
19
b00001000000010010000101000001011 <
b00000000000000000000000100101000 =
#193
09
#194
19
b00001100000011010000111000001111 <
b00000000000000000000000100101100 =
#195
09
#196
19
b00010000000100010001001000010011 <
b00000000000000000000000100110000 =
#197
09
#198
19
b00000000000000000000000000000000 <
b00000000000000000000000100110100 =
#199
09
#200
19
b00000000000000000000000100111000 =
#201
09
#202
19
b00000000000000000000000100111100 =
#203
09
#204
19
b00000000000000010000001000000011 <
b00000000000000000000000101000000 =
#205
09
#206
19
b00000100000001010000011000000111 <
b00000000000000000000000101000100 =
#207
09
#208
19
b00001000000010010000101000001011 <
b00000000000000000000000101001000 =
#209
09
#210
19
b00001100000011010000111000001111 <
b00000000000000000000000101001100 =
#211
09
#212
19
b00010000000100010001001000010011 <
b00000000000000000000000101010000 =
#213
09
#214
19
b00000000000000000000000000000000 <
b00000000000000000000000101010100 =
#215
09
#216
19
b00000000000000000000000101011000 =
#217
09
#218
19
b00000000000000000000000101011100 =
#219
09
#220
19
b00000000000000010000001000000011 <
b00000000000000000000000101100000 =
#221
09
#222
19
b00000100000001010000011000000111 <
b00000000000000000000000101100100 =
#223
09
#224
19
b00001000000010010000101000001011 <
b00000000000000000000000101101000 =
#225
09
#226
19
b00001100000011010000111000001111 <
b00000000000000000000000101101100 =
#227
09
#228
19
b00010000000100010001001000010011 <
b00000000000000000000000101110000 =
#229
09
#230
19
b00000000000000000000000000000000 <
b00000000000000000000000101110100 =
#231
09
#232
19
b00000000000000000000000101111000 =
#233
09
#234
19
b00000000000000000000000101111100 =
#235
09
#236
19
b00000000000000010000001000000011 <
b00000000000000000000000110000000 =
#237
09
#238
19
b00000100000001010000011000000111 <
b00000000000000000000000110000100 =
#239
09
#240
19
b00001000000010010000101000001011 <
b00000000000000000000000110001000 =
#241
09
#242
19
b00001100000011010000111000001111 <
b00000000000000000000000110001100 =
#243
09
#244
19
b00010000000100010001001000010011 <
b00000000000000000000000110010000 =
#245
09
#246
19
b00000000000000000000000000000000 <
b00000000000000000000000110010100 =
#247
09
#248
19
b00000000000000000000000110011000 =
#249
09
#250
19
b00000000000000000000000110011100 =
#251
09
#252
19
b00000000000000010000001000000011 <
b00000000000000000000000110100000 =
#253
09
#254
19
b00000100000001010000011000000111 <
b00000000000000000000000110100100 =
#255
09
#256
19
b00001000000010010000101000001011 <
b00000000000000000000000110101000 =
#257
09
#258
19
b00001100000011010000111000001111 <
b00000000000000000000000110101100 =
#259
09
#260
19
b00010000000100010001001000010011 <
b00000000000000000000000110110000 =
#261
09
#262
19
b00000000000000000000000000000000 <
b00000000000000000000000110110100 =
#263
09
#264
19
b00000000000000000000000110111000 =
#265
09
#266
19
b00000000000000000000000110111100 =
#267
09
#268
19
b00000000000000010000001000000011 <
b00000000000000000000000111000000 =
#269
09
#270
19
b00000100000001010000011000000111 <
b00000000000000000000000111000100 =
#271
09
#272
19
b00001000000010010000101000001011 <
b00000000000000000000000111001000 =
#273
09
#274
19
b00001100000011010000111000001111 <
b00000000000000000000000111001100 =
#275
09
#276
19
b00010000000100010001001000010011 <
b00000000000000000000000111010000 =
#277
09
#278
19
b00000000000000000000000000000000 <
b00000000000000000000000111010100 =
#279
09
#280
19
b00000000000000000000000111011000 =
#281
09
#282
19
b00000000000000000000000111011100 =
#283
09
#284
19
b00000000000000010000001000000011 <
b00000000000000000000000111100000 =
#285
09
#286
19
b00000100000001010000011000000111 <
b00000000000000000000000111100100 =
#287
09
#288
19
b00001000000010010000101000001011 <
b00000000000000000000000111101000 =
#289
09
#290
19
b00001100000011010000111000001111 <
b00000000000000000000000111101100 =
#291
09
#292
19
b00010000000100010001001000010011 <
b00000000000000000000000111110000 =
#293
09
#294
19
b00000000000000000000000000000000 <
b00000000000000000000000111110100 =
#295
09
#296
19
b00000000000000000000000111111000 =
#297
09
#298
19
b00000000000000000000000111111100 =
#299
09
#300
19
b00000000000000010000001000000011 <
b00000000000000000000001000000000 =
#301
09
#302
19
b00000100000001010000011000000111 <
b00000000000000000000001000000100 =
#303
09
#304
19
b00001000000010010000101000001011 <
b00000000000000000000001000001000 =
#305
09
#306
19
b00001100000011010000111000001111 <
b00000000000000000000001000001100 =
#307
09
#308
19
b00010000000100010001001000010011 <
b00000000000000000000001000010000 =
#309
09
#310
19
b00000000000000000000000000000000 <
b00000000000000000000001000010100 =
#311
09
#312
19
b00000000000000000000001000011000 =
#313
09
#314
19
b00000000000000000000001000011100 =
#315
09
#316
19
b00000000000000010000001000000011 <
b00000000000000000000001000100000 =
#317
09
#318
19
b00000100000001010000011000000111 <
b00000000000000000000001000100100 =
#319
09
#320
19
b00001000000010010000101000001011 <
b00000000000000000000001000101000 =
#321
09
#322
19
b00001100000011010000111000001111 <
b00000000000000000000001000101100 =
#323
09
#324
19
b00010000000100010001001000010011 <
b00000000000000000000001000110000 =
#325
09
#326
19
b00000000000000000000000000000000 <
b00000000000000000000001000110100 =
#327
09
#328
19
b00000000000000000000001000111000 =
#329
09
#330
19
b00000000000000000000001000111100 =
#331
09
#332
19
b00000000000000010000001000000011 <
b00000000000000000000001001000000 =
#333
09
#334
19
b00000100000001010000011000000111 <
b00000000000000000000001001000100 =
#335
09
#336
19
b00001000000010010000101000001011 <
b00000000000000000000001001001000 =
#337
09
#338
19
b00001100000011010000111000001111 <
b00000000000000000000001001001100 =
#339
09
#340
19
b00010000000100010001001000010011 <
b00000000000000000000001001010000 =
#341
09
#342
19
b00000000000000000000000000000000 <
b00000000000000000000001001010100 =
#343
09
#344
19
b00000000000000000000001001011000 =
#345
09
#346
19
b00000000000000000000001001011100 =
#347
09
#348
19
b00000000000000010000001000000011 <
b00000000000000000000001001100000 =
#349
09
#350
19
b00000100000001010000011000000111 <
b00000000000000000000001001100100 =
#351
09
#352
19
b00001000000010010000101000001011 <
b00000000000000000000001001101000 =
#353
09
#354
19
b00001100000011010000111000001111 <
b00000000000000000000001001101100 =
#355
09
#356
19
b00010000000100010001001000010011 <
b00000000000000000000001001110000 =
#357
09
#358
19
b00000000000000000000000000000000 <
b00000000000000000000001001110100 =
#359
09
#360
19
b00000000000000000000001001111000 =
#361
09
#362
19
b00000000000000000000001001111100 =
#363
09
#364
19
b00000000000000010000001000000011 <
b00000000000000000000001010000000 =
#365
09
#366
19
b00000100000001010000011000000111 <
b00000000000000000000001010000100 =
#367
09
#368
19
b00001000000010010000101000001011 <
b00000000000000000000001010001000 =
#369
09
#370
19
b00001100000011010000111000001111 <
b00000000000000000000001010001100 =
#371
09
#372
19
b00010000000100010001001000010011 <
b00000000000000000000001010010000 =
#373
09
#374
19
b00000000000000000000000000000000 <
b00000000000000000000001010010100 =
#375
09
#376
19
b00000000000000000000001010011000 =
#377
09
#378
19
b00000000000000000000001010011100 =
#379
09
#380
19
b00000000000000010000001000000011 <
b00000000000000000000001010100000 =
#381
09
#382
19
b00000100000001010000011000000111 <
b00000000000000000000001010100100 =
#383
09
#384
19
b00001000000010010000101000001011 <
b00000000000000000000001010101000 =
#385
09
#386
19
b00001100000011010000111000001111 <
b00000000000000000000001010101100 =
#387
09
#388
19
b00010000000100010001001000010011 <
b00000000000000000000001010110000 =
#389
09
#390
19
b00000000000000000000000000000000 <
b00000000000000000000001010110100 =
#391
09
#392
19
b00000000000000000000001010111000 =
#393
09
#394
19
b00000000000000000000001010111100 =
#395
09
#396
19
b00000000000000010000001000000011 <
b00000000000000000000001011000000 =
#397
09
#398
19
b00000100000001010000011000000111 <
b00000000000000000000001011000100 =
#399
09
#400
19
b00001000000010010000101000001011 <
b00000000000000000000001011001000 =
#401
09
#402
19
b00001100000011010000111000001111 <
b00000000000000000000001011001100 =
#403
09
#404
19
b00010000000100010001001000010011 <
b00000000000000000000001011010000 =
#405
09
#406
19
b00000000000000000000000000000000 <
b00000000000000000000001011010100 =
#407
09
#408
19
b00000000000000000000001011011000 =
#409
09
#410
19
b00000000000000000000001011011100 =
#411
09
#412
19
b00000000000000010000001000000011 <
b00000000000000000000001011100000 =
#413
09
#414
19
b00000100000001010000011000000111 <
b00000000000000000000001011100100 =
#415
09
#416
19
b00001000000010010000101000001011 <
b00000000000000000000001011101000 =
#417
09
#418
19
b00001100000011010000111000001111 <
b00000000000000000000001011101100 =
#419
09
#420
19
b00010000000100010001001000010011 <
b00000000000000000000001011110000 =
#421
09
#422
19
b00000000000000000000000000000000 <
b00000000000000000000001011110100 =
#423
09
#424
19
b00000000000000000000001011111000 =
#425
09
#426
19
b00000000000000000000001011111100 =
#427
09
#428
19
b00000000000000010000001000000011 <
b00000000000000000000001100000000 =
#429
09
#430
19
b00000100000001010000011000000111 <
b00000000000000000000001100000100 =
#431
09
#432
19
b00001000000010010000101000001011 <
b00000000000000000000001100001000 =
#433
09
#434
19
b00001100000011010000111000001111 <
b00000000000000000000001100001100 =
#435
09
#436
19
b00010000000100010001001000010011 <
b00000000000000000000001100010000 =
#437
09
#438
19
b00000000000000000000000000000000 <
b00000000000000000000001100010100 =
#439
09
#440
19
b00000000000000000000001100011000 =
#441
09
#442
19
b00000000000000000000001100011100 =
#443
09
#444
19
b00000000000000010000001000000011 <
b00000000000000000000001100100000 =
#445
09
#446
19
b00000100000001010000011000000111 <
b00000000000000000000001100100100 =
#447
09
#448
19
b00001000000010010000101000001011 <
b00000000000000000000001100101000 =
#449
09
#450
19
b00001100000011010000111000001111 <
b00000000000000000000001100101100 =
#451
09
#452
19
b00010000000100010001001000010011 <
b00000000000000000000001100110000 =
#453
09
#454
19
b00000000000000000000000000000000 <
b00000000000000000000001100110100 =
#455
09
#456
19
b00000000000000000000001100111000 =
#457
09
#458
19
b00000000000000000000001100111100 =
#459
09
#460
19
b00000000000000010000001000000011 <
b00000000000000000000001101000000 =
#461
09
#462
19
b00000100000001010000011000000111 <
b00000000000000000000001101000100 =
#463
09
#464
19
b00001000000010010000101000001011 <
b00000000000000000000001101001000 =
#465
09
#466
19
b00001100000011010000111000001111 <
b00000000000000000000001101001100 =
#467
09
#468
19
b00010000000100010001001000010011 <
b00000000000000000000001101010000 =
#469
09
#470
19
b00000000000000000000000000000000 <
b00000000000000000000001101010100 =
#471
09
#472
19
b00000000000000000000001101011000 =
#473
09
#474
19
b00000000000000000000001101011100 =
#475
09
#476
19
b00000000000000010000001000000011 <
b00000000000000000000001101100000 =
#477
09
#478
19
b00000100000001010000011000000111 <
b00000000000000000000001101100100 =
#479
09
#480
19
b00001000000010010000101000001011 <
b00000000000000000000001101101000 =
#481
09
#482
19
b00001100000011010000111000001111 <
b00000000000000000000001101101100 =
#483
09
#484
19
b00010000000100010001001000010011 <
b00000000000000000000001101110000 =
#485
09
#486
19
b00000000000000000000000000000000 <
b00000000000000000000001101110100 =
#487
09
#488
19
b00000000000000000000001101111000 =
#489
09
#490
19
b00000000000000000000001101111100 =
#491
09
#492
19
b00000000000000010000001000000011 <
b00000000000000000000001110000000 =
#493
09
#494
19
b00000100000001010000011000000111 <
b00000000000000000000001110000100 =
#495
09
#496
19
b00001000000010010000101000001011 <
b00000000000000000000001110001000 =
#497
09
#498
19
b00001100000011010000111000001111 <
b00000000000000000000001110001100 =
#499
09
#500
19
b00010000000100010001001000010011 <
b00000000000000000000001110010000 =
#501
09
#502
19
b00000000000000000000000000000000 <
b00000000000000000000001110010100 =
#503
09
#504
19
b00000000000000000000001110011000 =
#505
09
#506
19
b00000000000000000000001110011100 =
#507
09
#508
19
b00000000000000010000001000000011 <
b00000000000000000000001110100000 =
#509
09
#510
19
b00000100000001010000011000000111 <
b00000000000000000000001110100100 =
#511
09
#512
19
b00001000000010010000101000001011 <
b00000000000000000000001110101000 =
#513
09
#514
19
b00001100000011010000111000001111 <
b00000000000000000000001110101100 =
#515
09
#516
19
b00010000000100010001001000010011 <
b00000000000000000000001110110000 =
#517
09
#518
19
b00000000000000000000000000000000 <
b00000000000000000000001110110100 =
#519
09
#520
19
b00000000000000000000001110111000 =
#521
09
#522
19
b00000000000000000000001110111100 =
#523
09
#524
19
b00000000000000010000001000000011 <
b00000000000000000000001111000000 =
#525
09
#526
19
b00000100000001010000011000000111 <
b00000000000000000000001111000100 =
#527
09
#528
19
b00001000000010010000101000001011 <
b00000000000000000000001111001000 =
#529
09
#530
19
b00001100000011010000111000001111 <
b00000000000000000000001111001100 =
#531
09
#532
19
b00010000000100010001001000010011 <
b00000000000000000000001111010000 =
#533
09
#534
19
b00000000000000000000000000000000 <
b00000000000000000000001111010100 =
#535
09
#536
19
b00000000000000000000001111011000 =
#537
09
#538
19
b00000000000000000000001111011100 =
#539
09
#540
19
b00000000000000010000001000000011 <
b00000000000000000000001111100000 =
#541
09
#542
19
b00000100000001010000011000000111 <
b00000000000000000000001111100100 =
#543
09
#544
19
b00001000000010010000101000001011 <
b00000000000000000000001111101000 =
#545
09
#546
19
b00001100000011010000111000001111 <
b00000000000000000000001111101100 =
#547
09
#548
19
b00010000000100010001001000010011 <
b00000000000000000000001111110000 =
#549
09
#550
19
b00000000000000000000000000000000 <
b00000000000000000000001111110100 =
#551
09
#552
19
b00000000000000000000001111111000 =
#553
09
#554
19
b00000000000000000000001111111100 =
#555
09
#556
19
b00000000000000010000001000000011 <
b00000000000000000000010000000000 =
#557
09
#558
19
b00000100000001010000011000000111 <
b00000000000000000000010000000100 =
#559
09
#560
19
b00001000000010010000101000001011 <
b00000000000000000000010000001000 =
#561
09
#562
19
b00001100000011010000111000001111 <
b00000000000000000000010000001100 =
#563
09
#564
19
b00010000000100010001001000010011 <
b00000000000000000000010000010000 =
#565
09
#566
19
b00000000000000000000000000000000 <
b00000000000000000000010000010100 =
#567
09
#568
19
b00000000000000000000010000011000 =
#569
09
#570
19
b00000000000000000000010000011100 =
#571
09
#572
19
b00000000000000010000001000000011 <
b00000000000000000000010000100000 =
#573
09
#574
19
b00000100000001010000011000000111 <
b00000000000000000000010000100100 =
#575
09
#576
19
b00001000000010010000101000001011 <
b00000000000000000000010000101000 =
#577
09
#578
19
b00001100000011010000111000001111 <
b00000000000000000000010000101100 =
#579
09
#580
19
b00010000000100010001001000010011 <
b00000000000000000000010000110000 =
#581
09
#582
19
b00000000000000000000000000000000 <
b00000000000000000000010000110100 =
#583
09
#584
19
b00000000000000000000010000111000 =
#585
09
#586
19
b00000000000000000000010000111100 =
#587
09
#588
19
b00000000000000010000001000000011 <
b00000000000000000000010001000000 =
#589
09
#590
19
b00000100000001010000011000000111 <
b00000000000000000000010001000100 =
#591
09
#592
19
b00001000000010010000101000001011 <
b00000000000000000000010001001000 =
#593
09
#594
19
b00001100000011010000111000001111 <
b00000000000000000000010001001100 =
#595
09
#596
19
b00010000000100010001001000010011 <
b00000000000000000000010001010000 =
#597
09
#598
19
b00000000000000000000000000000000 <
b00000000000000000000010001010100 =
#599
09
#600
19
b00000000000000000000010001011000 =
#601
09
#602
19
b00000000000000000000010001011100 =
#603
09
#604
19
b00000000000000010000001000000011 <
b00000000000000000000010001100000 =
#605
09
#606
19
b00000100000001010000011000000111 <
b00000000000000000000010001100100 =
#607
09
#608
19
b00001000000010010000101000001011 <
b00000000000000000000010001101000 =
#609
09
#610
19
b00001100000011010000111000001111 <
b00000000000000000000010001101100 =
#611
09
#612
19
b00010000000100010001001000010011 <
b00000000000000000000010001110000 =
#613
09
#614
19
b00000000000000000000000000000000 <
b00000000000000000000010001110100 =
#615
09
#616
19
b00000000000000000000010001111000 =
#617
09
#618
19
b00000000000000000000010001111100 =
#619
09
#620
19
b00000000000000010000001000000011 <
b00000000000000000000010010000000 =
#621
09
#622
19
b00000100000001010000011000000111 <
b00000000000000000000010010000100 =
#623
09
#624
19
b00001000000010010000101000001011 <
b00000000000000000000010010001000 =
#625
09
#626
19
b00001100000011010000111000001111 <
b00000000000000000000010010001100 =
#627
09
#628
19
b00010000000100010001001000010011 <
b00000000000000000000010010010000 =
#629
09
#630
19
b00000000000000000000000000000000 <
b00000000000000000000010010010100 =
#631
09
#632
19
b00000000000000000000010010011000 =
#633
09
#634
19
b00000000000000000000010010011100 =
#635
09
#636
19
b00000000000000010000001000000011 <
b00000000000000000000010010100000 =
#637
09
#638
19
b00000100000001010000011000000111 <
b00000000000000000000010010100100 =
#639
09
#640
19
b00001000000010010000101000001011 <
b00000000000000000000010010101000 =
#641
09
#642
19
b00001100000011010000111000001111 <
b00000000000000000000010010101100 =
#643
09
#644
19
b00010000000100010001001000010011 <
b00000000000000000000010010110000 =
#645
09
#646
19
b00000000000000000000000000000000 <
b00000000000000000000010010110100 =
#647
09
#648
19
b00000000000000000000010010111000 =
#649
09
#650
19
b00000000000000000000010010111100 =
#651
09
#652
19
b00000000000000010000001000000011 <
b00000000000000000000010011000000 =
#653
09
#654
19
b00000100000001010000011000000111 <
b00000000000000000000010011000100 =
#655
09
#656
19
b00001000000010010000101000001011 <
b00000000000000000000010011001000 =
#657
09
#658
19
b00001100000011010000111000001111 <
b00000000000000000000010011001100 =
#659
09
#660
19
b00010000000100010001001000010011 <
b00000000000000000000010011010000 =
#661
09
#662
19
b00000000000000000000000000000000 <
b00000000000000000000010011010100 =
#663
09
#664
19
b00000000000000000000010011011000 =
#665
09
#666
19
b00000000000000000000010011011100 =
#667
09
#668
19
b00000000000000010000001000000011 <
b00000000000000000000010011100000 =
#669
09
#670
19
b00000100000001010000011000000111 <
b00000000000000000000010011100100 =
#671
09
#672
19
b00001000000010010000101000001011 <
b00000000000000000000010011101000 =
#673
09
#674
19
b00001100000011010000111000001111 <
b00000000000000000000010011101100 =
#675
09
#676
19
b00010000000100010001001000010011 <
b00000000000000000000010011110000 =
#677
09
#678
19
b00000000000000000000000000000000 <
b00000000000000000000010011110100 =
#679
09
#680
19
b00000000000000000000010011111000 =
#681
09
#682
19
b00000000000000000000010011111100 =
#683
09
#684
19
b00000000000000010000001000000011 <
b00000000000000000000010100000000 =
#685
09
#686
19
b00000100000001010000011000000111 <
b00000000000000000000010100000100 =
#687
09
#688
19
b00001000000010010000101000001011 <
b00000000000000000000010100001000 =
#689
09
#690
19
b00001100000011010000111000001111 <
b00000000000000000000010100001100 =
#691
09
#692
19
b00010000000100010001001000010011 <
b00000000000000000000010100010000 =
#693
09
#694
19
b00000000000000000000000000000000 <
b00000000000000000000010100010100 =
#695
09
