PC_ROM/instr_mem.sv
module instr_mem #(
    parameter   ADDRESS_WIDTH = 32,
                DATAOUT_WIDTH = 32,
                DATA_WIDTH = 8
)(
    input logic [ADDRESS_WIDTH-1:0] A,
    output logic [DATAOUT_WIDTH-1:0] RD
);

logic [DATA_WIDTH-1:0] rom_array [20:0]; // the parameter after the rom_array is the size of the .mem file

initial begin
        $display("Loading rom.");
        $readmemh("test1.mem", rom_array);
end;

assign RD = {rom_array [A],rom_array [A+1],rom_array [A+2],rom_array [A+3]};

endmodule

PC_ROM/blue_part.sv
module blue_part #(
    parameter address_width = 8
)(
    input logic                            PCsrc, // output from control unit
    input logic                            clk,
    input logic                            rst,
    input logic [address_width-1:0]        ImmOp, // output from "sign extend" block
    output logic [address_width-1:0]       PC
);

//logic       next_pc;

always_ff@(posedge clk) begin
    if (rst)        PC <= {address_width{1'b0}};
    else if (PCsrc)      PC <= PC + ImmOp;
    else            PC <= PC + 4;
end

endmodule

PC_ROM/top.sv
module top#(
    parameter ADDRESS_WIDTH = 8,
    DATAOUT_WIDTH = 32
)(
    input logic                            PCsrc, // output from control unit
    input logic                            clk,
    input logic                            rst,
    input logic [ADDRESS_WIDTH-1:0]        ImmOp, // output from "sign extend" block
  //  output logic [ADDRESS_WIDTH-1:0]       PC,
  //  input logic [ADDRESS_WIDTH-1:0]        A,
    output logic [DATAOUT_WIDTH-1:0]       RD
);

logic [ADDRESS_WIDTH-1:0]        A;

blue_part pc(
    .PCsrc(PCsrc),
    .clk(clk),
    .rst(rst),
    .ImmOp(ImmOp),
    .PC(A)
);

instr_mem mem(
    .A(A),
    .RD(RD)
);

endmodule

PC_ROM/top.vcd
$version Generated by VerilatedVcd $end
$date Fri Nov 18 18:26:04 2022 $end
$timescale 1ps $end

 $scope module TOP $end
  $var wire  8 & ImmOp [7:0] $end
  $var wire  1 # PCsrc $end
  $var wire 32 ' RD [31:0] $end
  $var wire  1 $ clk $end
  $var wire  1 % rst $end
  $scope module top $end
   $var wire  8 ( A [7:0] $end
   $var wire 32 ) ADDRESS_WIDTH [31:0] $end
   $var wire 32 * DATAOUT_WIDTH [31:0] $end
   $var wire  8 & ImmOp [7:0] $end
   $var wire  1 # PCsrc $end
   $var wire 32 ' RD [31:0] $end
   $var wire  1 $ clk $end
   $var wire  1 % rst $end
   $scope module mem $end
    $var wire  8 ( A [7:0] $end
    $var wire 32 ) ADDRESS_WIDTH [31:0] $end
    $var wire 32 * DATAOUT_WIDTH [31:0] $end
    $var wire 32 ) DATA_WIDTH [31:0] $end
    $var wire 32 ' RD [31:0] $end
   $upscope $end
   $scope module pc $end
    $var wire  8 & ImmOp [7:0] $end
    $var wire  8 ( PC [7:0] $end
    $var wire  1 # PCsrc $end
    $var wire 32 ) address_width [31:0] $end
    $var wire  1 $ clk $end
    $var wire  1 % rst $end
   $upscope $end
  $upscope $end
 $upscope $end
$enddefinitions $end


#0
0#
1$
0%
b00001000 &
b00000000000000000000000000000000 '
b00000000 (
b00000000000000000000000000001000 )
b00000000000000000000000000100000 *
#1
0$
b00000000000000010000001000000011 '
#2
1$
b00000100000001010000011000000111 '
b00000100 (
#3
0$
#4
1$
b00001000000010010000101000001011 '
b00001000 (
#5
0$
#6
1$
b00001100000011010000111000001111 '
b00001100 (
#7
0$
#8
1$
b00010000000100010001001000010011 '
b00010000 (
#9
0$
#10
1$
b00010100000101010001011000010111 '
b00010100 (
#11
0$
#12
1$
b00011000000110010001101000011011 '
b00011000 (
#13
0$
#14
1$
b00011100000111010001111000011111 '
b00011100 (
#15
0$
#16
1$
b00100000001000010010001000100011 '
b00100000 (
#17
0$
#18
1$
b00100100001001010010011000100111 '
b00100100 (
#19
0$
#20
1$
b00101000001010010010101000101011 '
b00101000 (
#21
0$
#22
1#
1$
b00101100001011010010111000101111 '
b00101100 (
#23
0$
#24
0#
1$
b00110100001101010011011000110111 '
b00110100 (
#25
0$
#26
1$
b00111000001110010011101000111011 '
b00111000 (
#27
0$
#28
1$
b00111100001111010011111000111111 '
b00111100 (
#29
0$
#30
1$
b01000000010000010100001001000011 '
b01000000 (
#31
0$
#32
1$
b01000100010001010100011001000111 '
b01000100 (
#33
0$
#34
1$
b01001000010010010100101001001011 '
b01001000 (
#35
0$
#36
1$
b01001100010011010100111001001111 '
b01001100 (
#37
0$
#38
1$
b01010000010100010101001001010011 '
b01010000 (
#39
0$
#40
1$
b01010100010101010101011001010111 '
b01010100 (
#41
0$
#42
1$
1%
b01011000010110010101101001011011 '
b01011000 (
#43
0$
#44
1$
0%
b00000000000000010000001000000011 '
b00000000 (
#45
0$
#46
1$
b00000100000001010000011000000111 '
b00000100 (
#47
0$
#48
1$
b00001000000010010000101000001011 '
b00001000 (
#49
0$
#50
1$
b00001100000011010000111000001111 '
b00001100 (
#51
0$
#52
1$
b00010000000100010001001000010011 '
b00010000 (
#53
0$
#54
1$
b00010100000101010001011000010111 '
b00010100 (
#55
0$
#56
1$
b00011000000110010001101000011011 '
b00011000 (
#57
0$
#58
1$
b00011100000111010001111000011111 '
b00011100 (
#59
0$
#60
1$
b00100000001000010010001000100011 '
b00100000 (
#61
0$
#62
1$
b00100100001001010010011000100111 '
b00100100 (
#63
0$
#64
1$
b00101000001010010010101000101011 '
b00101000 (
#65
0$
#66
1$
b00101100001011010010111000101111 '
b00101100 (
#67
0$
#68
1$
b00110000001100010011001000110011 '
b00110000 (
#69
0$
#70
1$
b00110100001101010011011000110111 '
b00110100 (
#71
0$
#72
1$
b00111000001110010011101000111011 '
b00111000 (
#73
0$
#74
1$
b00111100001111010011111000111111 '
b00111100 (
#75
0$
#76
1$
b01000000010000010100001001000011 '
b01000000 (
#77
0$
#78
1$
b01000100010001010100011001000111 '
b01000100 (
#79
0$
#80
1$
b01001000010010010100101001001011 '
b01001000 (
#81
0$
#82
1$
b01001100010011010100111001001111 '
b01001100 (
#83
0$
#84
1$
b01010000010100010101001001010011 '
b01010000 (
#85
0$
#86
1$
b01010100010101010101011001010111 '
b01010100 (
#87
0$
#88
1$
b01011000010110010101101001011011 '
b01011000 (
#89
0$
#90
1$
b01011100010111010101111001011111 '
b01011100 (
#91
0$
#92
1$
b01100000011000010110001001100011 '
b01100000 (
#93
0$
#94
1$
b01100100011001010110011001100111 '
b01100100 (
#95
0$
#96
1$
b01101000011010010110101001101011 '
b01101000 (
#97
0$
#98
1$
b01101100011011010110111001101111 '
b01101100 (
#99
0$
#100
1$
b01110000011100010111001001110011 '
b01110000 (
#101
0$
#102
1$
b01110100011101010111011001110111 '
b01110100 (
#103
0$
#104
1$
b01111000011110010111101001111011 '
b01111000 (
#105
0$
#106
1$
b01111100011111010111111001111111 '
b01111100 (
#107
0$
#108
1$
b10000000100000011000001010000011 '
b10000000 (
#109
0$
#110
1$
b10000100100001011000011010000111 '
b10000100 (
#111
0$
#112
1$
b10001000100010011000101010001011 '
b10001000 (
#113
0$
#114
1$
b10001100100011011000111010001111 '
b10001100 (
#115
0$
#116
1$
b10010000100100011001001010010011 '
b10010000 (
#117
0$
#118
1$
b10010100100101011001011010010111 '
b10010100 (
#119
0$
#120
1$
b10011000100110011001101010011011 '
b10011000 (
#121
0$
#122
1$
b10011100100111011001111010011111 '
b10011100 (
#123
0$
#124
1$
b10100000101000011010001010100011 '
b10100000 (
#125
0$
#126
1$
b10100100101001011010011010100111 '
b10100100 (
#127
0$
#128
1$
b10101000101010011010101010101011 '
b10101000 (
#129
0$
#130
1$
b10101100101011011010111010101111 '
b10101100 (
#131
0$
#132
1$
b10110000101100011011001010110011 '
b10110000 (
#133
0$
#134
1$
b10110100101101011011011010110111 '
b10110100 (
#135
0$
#136
1$
b10111000101110011011101010111011 '
b10111000 (
#137
0$
#138
1$
b10111100101111011011111010111111 '
b10111100 (
#139
0$
#140
1$
b11000000110000011100001011000011 '
b11000000 (
#141
0$
#142
1$
b11000100110001011100011011000111 '
b11000100 (
#143
0$
#144
1$
b11001000110010011100101011001011 '
b11001000 (
#145
0$
#146
1$
b11001100110011011100111011001111 '
b11001100 (
#147
0$
#148
1$
b11010000110100011101001011010011 '
b11010000 (
#149
0$
#150
1$
b11010100110101011101011011010111 '
b11010100 (
#151
0$
#152
1$
b11011000110110011101101011011011 '
b11011000 (
#153
0$
#154
1$
b11011100110111011101111011011111 '
b11011100 (
#155
0$
#156
1$
b11100000111000011110001011100011 '
b11100000 (
#157
0$
#158
1$
b11100100111001011110011011100111 '
b11100100 (
#159
0$
#160
1$
b11101000111010011110101011101011 '
b11101000 (
#161
0$
#162
1$
b11101100111011011110111011101111 '
b11101100 (
#163
0$
#164
1$
b11110000111100011111001011110011 '
b11110000 (
#165
0$
#166
1$
b11110100111101011111011011110111 '
b11110100 (
#167
0$
#168
1$
b11111000111110011111101011111011 '
b11111000 (
#169
0$
#170
1$
b11111100111111011111111011111111 '
b11111100 (
#171
0$
#172
1$
b00000000000000010000001000000011 '
b00000000 (
#173
0$
#174
1$
b00000100000001010000011000000111 '
b00000100 (
#175
0$
#176
1$
b00001000000010010000101000001011 '
b00001000 (
#177
0$
#178
1$
b00001100000011010000111000001111 '
b00001100 (
#179
0$
#180
1$
b00010000000100010001001000010011 '
b00010000 (
#181
0$
#182
1$
b00010100000101010001011000010111 '
b00010100 (
#183
0$
#184
1$
b00011000000110010001101000011011 '
b00011000 (
#185
0$
#186
1$
b00011100000111010001111000011111 '
b00011100 (
#187
0$
#188
1$
b00100000001000010010001000100011 '
b00100000 (
#189
0$
#190
1$
b00100100001001010010011000100111 '
b00100100 (
#191
0$
#192
1$
b00101000001010010010101000101011 '
b00101000 (
#193
0$
#194
1$
b00101100001011010010111000101111 '
b00101100 (
#195
0$
#196
1$
b00110000001100010011001000110011 '
b00110000 (
#197
0$
#198
1$
b00110100001101010011011000110111 '
b00110100 (
#199
0$
#200
1$
b00111000001110010011101000111011 '
b00111000 (
#201
0$
#202
1$
b00111100001111010011111000111111 '
b00111100 (
#203
0$
#204
1$
b01000000010000010100001001000011 '
b01000000 (
#205
0$
#206
1$
b01000100010001010100011001000111 '
b01000100 (
#207
0$
#208
1$
b01001000010010010100101001001011 '
b01001000 (
#209
0$
#210
1$
b01001100010011010100111001001111 '
b01001100 (
#211
0$
#212
1$
b01010000010100010101001001010011 '
b01010000 (
#213
0$
#214
1$
b01010100010101010101011001010111 '
b01010100 (
#215
0$
#216
1$
b01011000010110010101101001011011 '
b01011000 (
#217
0$
#218
1$
b01011100010111010101111001011111 '
b01011100 (
#219
0$
#220
1$
b01100000011000010110001001100011 '
b01100000 (
#221
0$
#222
1$
b01100100011001010110011001100111 '
b01100100 (
#223
0$
#224
1$
b01101000011010010110101001101011 '
b01101000 (
#225
0$
#226
1$
b01101100011011010110111001101111 '
b01101100 (
#227
0$
#228
1$
b01110000011100010111001001110011 '
b01110000 (
#229
0$
#230
1$
b01110100011101010111011001110111 '
b01110100 (
#231
0$
#232
1$
b01111000011110010111101001111011 '
b01111000 (
#233
0$
#234
1$
b01111100011111010111111001111111 '
b01111100 (
#235
0$
#236
1$
b10000000100000011000001010000011 '
b10000000 (
#237
0$
#238
1$
b10000100100001011000011010000111 '
b10000100 (
#239
0$
#240
1$
b10001000100010011000101010001011 '
b10001000 (
#241
0$
#242
1$
b10001100100011011000111010001111 '
b10001100 (
#243
0$
#244
1$
b10010000100100011001001010010011 '
b10010000 (
#245
0$
#246
1$
b10010100100101011001011010010111 '
b10010100 (
#247
0$
#248
1$
b10011000100110011001101010011011 '
b10011000 (
#249
0$
#250
1$
b10011100100111011001111010011111 '
b10011100 (
#251
0$
#252
1$
b10100000101000011010001010100011 '
b10100000 (
#253
0$
#254
1$
b10100100101001011010011010100111 '
b10100100 (
#255
0$
#256
1$
b10101000101010011010101010101011 '
b10101000 (
#257
0$
#258
1$
b10101100101011011010111010101111 '
b10101100 (
#259
0$
#260
1$
b10110000101100011011001010110011 '
b10110000 (
#261
0$
#262
1$
b10110100101101011011011010110111 '
b10110100 (
#263
0$
#264
1$
b10111000101110011011101010111011 '
b10111000 (
#265
0$
#266
1$
b10111100101111011011111010111111 '
b10111100 (
#267
0$
#268
1$
b11000000110000011100001011000011 '
b11000000 (
#269
0$
#270
1$
b11000100110001011100011011000111 '
b11000100 (
#271
0$
#272
1$
b11001000110010011100101011001011 '
b11001000 (
#273
0$
#274
1$
b11001100110011011100111011001111 '
b11001100 (
#275
0$
#276
1$
b11010000110100011101001011010011 '
b11010000 (
#277
0$
#278
1$
b11010100110101011101011011010111 '
b11010100 (
#279
0$
#280
1$
b11011000110110011101101011011011 '
b11011000 (
#281
0$
#282
1$
b11011100110111011101111011011111 '
b11011100 (
#283
0$
#284
1$
b11100000111000011110001011100011 '
b11100000 (
#285
0$
#286
1$
b11100100111001011110011011100111 '
b11100100 (
#287
0$
#288
1$
b11101000111010011110101011101011 '
b11101000 (
#289
0$
#290
1$
b11101100111011011110111011101111 '
b11101100 (
#291
0$
#292
1$
b11110000111100011111001011110011 '
b11110000 (
#293
0$
#294
1$
b11110100111101011111011011110111 '
b11110100 (
#295
0$
#296
1$
b11111000111110011111101011111011 '
b11111000 (
#297
0$
#298
1$
b11111100111111011111111011111111 '
b11111100 (
#299
0$
#300
1$
b00000000000000010000001000000011 '
b00000000 (
#301
0$
#302
1$
b00000100000001010000011000000111 '
b00000100 (
#303
0$
#304
1$
b00001000000010010000101000001011 '
b00001000 (
#305
0$
#306
1$
b00001100000011010000111000001111 '
b00001100 (
#307
0$
#308
1$
b00010000000100010001001000010011 '
b00010000 (
#309
0$
#310
1$
b00010100000101010001011000010111 '
b00010100 (
#311
0$
#312
1$
b00011000000110010001101000011011 '
b00011000 (
#313
0$
#314
1$
b00011100000111010001111000011111 '
b00011100 (
#315
0$
#316
1$
b00100000001000010010001000100011 '
b00100000 (
#317
0$
#318
1$
b00100100001001010010011000100111 '
b00100100 (
#319
0$
#320
1$
b00101000001010010010101000101011 '
b00101000 (
#321
0$
#322
1$
b00101100001011010010111000101111 '
b00101100 (
#323
0$
#324
1$
b00110000001100010011001000110011 '
b00110000 (
#325
0$
#326
1$
b00110100001101010011011000110111 '
b00110100 (
#327
0$
#328
1$
b00111000001110010011101000111011 '
b00111000 (
#329
0$
#330
1$
b00111100001111010011111000111111 '
b00111100 (
#331
0$
#332
1$
b01000000010000010100001001000011 '
b01000000 (
#333
0$
#334
1$
b01000100010001010100011001000111 '
b01000100 (
#335
0$
#336
1$
b01001000010010010100101001001011 '
b01001000 (
#337
0$
#338
1$
b01001100010011010100111001001111 '
b01001100 (
#339
0$
#340
1$
b01010000010100010101001001010011 '
b01010000 (
#341
0$
#342
1$
b01010100010101010101011001010111 '
b01010100 (
#343
0$
#344
1$
b01011000010110010101101001011011 '
b01011000 (
#345
0$
#346
1$
b01011100010111010101111001011111 '
b01011100 (
#347
0$
#348
1$
b01100000011000010110001001100011 '
b01100000 (
#349
0$
#350
1$
b01100100011001010110011001100111 '
b01100100 (
#351
0$
#352
1$
b01101000011010010110101001101011 '
b01101000 (
#353
0$
#354
1$
b01101100011011010110111001101111 '
b01101100 (
#355
0$
#356
1$
b01110000011100010111001001110011 '
b01110000 (
#357
0$
#358
1$
b01110100011101010111011001110111 '
b01110100 (
#359
0$
#360
1$
b01111000011110010111101001111011 '
b01111000 (
#361
0$
#362
1$
b01111100011111010111111001111111 '
b01111100 (
#363
0$
#364
1$
b10000000100000011000001010000011 '
b10000000 (
#365
0$
#366
1$
b10000100100001011000011010000111 '
b10000100 (
#367
0$
#368
1$
b10001000100010011000101010001011 '
b10001000 (
#369
0$
#370
1$
b10001100100011011000111010001111 '
b10001100 (
#371
0$
#372
1$
b10010000100100011001001010010011 '
b10010000 (
#373
0$
#374
1$
b10010100100101011001011010010111 '
b10010100 (
#375
0$
#376
1$
b10011000100110011001101010011011 '
b10011000 (
#377
0$
#378
1$
b10011100100111011001111010011111 '
b10011100 (
#379
0$
#380
1$
b10100000101000011010001010100011 '
b10100000 (
#381
0$
#382
1$
b10100100101001011010011010100111 '
b10100100 (
#383
0$
#384
1$
b10101000101010011010101010101011 '
b10101000 (
#385
0$
#386
1$
b10101100101011011010111010101111 '
b10101100 (
#387
0$
#388
1$
b10110000101100011011001010110011 '
b10110000 (
#389
0$
#390
1$
b10110100101101011011011010110111 '
b10110100 (
#391
0$
#392
1$
b10111000101110011011101010111011 '
b10111000 (
#393
0$
#394
1$
b10111100101111011011111010111111 '
b10111100 (
#395
0$
#396
1$
b11000000110000011100001011000011 '
b11000000 (
#397
0$
#398
1$
b11000100110001011100011011000111 '
b11000100 (
#399
0$
#400
1$
b11001000110010011100101011001011 '
b11001000 (
#401
0$
#402
1$
b11001100110011011100111011001111 '
b11001100 (
#403
0$
#404
1$
b11010000110100011101001011010011 '
b11010000 (
#405
0$
#406
1$
b11010100110101011101011011010111 '
b11010100 (
#407
0$
#408
1$
b11011000110110011101101011011011 '
b11011000 (
#409
0$
#410
1$
b11011100110111011101111011011111 '
b11011100 (
#411
0$
#412
1$
b11100000111000011110001011100011 '
b11100000 (
#413
0$
#414
1$
b11100100111001011110011011100111 '
b11100100 (
#415
0$
#416
1$
b11101000111010011110101011101011 '
b11101000 (
#417
0$
#418
1$
b11101100111011011110111011101111 '
b11101100 (
#419
0$
#420
1$
b11110000111100011111001011110011 '
b11110000 (
#421
0$
#422
1$
b11110100111101011111011011110111 '
b11110100 (
#423
0$
#424
1$
b11111000111110011111101011111011 '
b11111000 (
#425
0$
#426
1$
b11111100111111011111111011111111 '
b11111100 (
#427
0$
#428
1$
b00000000000000010000001000000011 '
b00000000 (
#429
0$
#430
1$
b00000100000001010000011000000111 '
b00000100 (
#431
0$
#432
1$
b00001000000010010000101000001011 '
b00001000 (
#433
0$
#434
1$
b00001100000011010000111000001111 '
b00001100 (
#435
0$
#436
1$
b00010000000100010001001000010011 '
b00010000 (
#437
0$
#438
1$
b00010100000101010001011000010111 '
b00010100 (
#439
0$
#440
1$
b00011000000110010001101000011011 '
b00011000 (
#441
0$
#442
1$
b00011100000111010001111000011111 '
b00011100 (
#443
0$
#444
1$
b00100000001000010010001000100011 '
b00100000 (
#445
0$
#446
1$
b00100100001001010010011000100111 '
b00100100 (
#447
0$
#448
1$
b00101000001010010010101000101011 '
b00101000 (
#449
0$
#450
1$
b00101100001011010010111000101111 '
b00101100 (
#451
0$
#452
1$
b00110000001100010011001000110011 '
b00110000 (
#453
0$
#454
1$
b00110100001101010011011000110111 '
b00110100 (
#455
0$
#456
1$
b00111000001110010011101000111011 '
b00111000 (
#457
0$
#458
1$
b00111100001111010011111000111111 '
b00111100 (
#459
0$
#460
1$
b01000000010000010100001001000011 '
b01000000 (
#461
0$
#462
1$
b01000100010001010100011001000111 '
b01000100 (
#463
0$
#464
1$
b01001000010010010100101001001011 '
b01001000 (
#465
0$
#466
1$
b01001100010011010100111001001111 '
b01001100 (
#467
0$
#468
1$
b01010000010100010101001001010011 '
b01010000 (
#469
0$
#470
1$
b01010100010101010101011001010111 '
b01010100 (
#471
0$
#472
1$
b01011000010110010101101001011011 '
b01011000 (
#473
0$
#474
1$
b01011100010111010101111001011111 '
b01011100 (
#475
0$
#476
1$
b01100000011000010110001001100011 '
b01100000 (
#477
0$
#478
1$
b01100100011001010110011001100111 '
b01100100 (
#479
0$
#480
1$
b01101000011010010110101001101011 '
b01101000 (
#481
0$
#482
1$
b01101100011011010110111001101111 '
b01101100 (
#483
0$
#484
1$
b01110000011100010111001001110011 '
b01110000 (
#485
0$
#486
1$
b01110100011101010111011001110111 '
b01110100 (
#487
0$
#488
1$
b01111000011110010111101001111011 '
b01111000 (
#489
0$
#490
1$
b01111100011111010111111001111111 '
b01111100 (
#491
0$
#492
1$
b10000000100000011000001010000011 '
b10000000 (
#493
0$
#494
1$
b10000100100001011000011010000111 '
b10000100 (
#495
0$
#496
1$
b10001000100010011000101010001011 '
b10001000 (
#497
0$
#498
1$
b10001100100011011000111010001111 '
b10001100 (
#499
0$
#500
1$
b10010000100100011001001010010011 '
b10010000 (
#501
0$
#502
1$
b10010100100101011001011010010111 '
b10010100 (
#503
0$
#504
1$
b10011000100110011001101010011011 '
b10011000 (
#505
0$
#506
1$
b10011100100111011001111010011111 '
b10011100 (
#507
0$
#508
1$
b10100000101000011010001010100011 '
b10100000 (
#509
0$
#510
1$
b10100100101001011010011010100111 '
b10100100 (
#511
0$
#512
1$
b10101000101010011010101010101011 '
b10101000 (
#513
0$
#514
1$
b10101100101011011010111010101111 '
b10101100 (
#515
0$
#516
1$
b10110000101100011011001010110011 '
b10110000 (
#517
0$
#518
1$
b10110100101101011011011010110111 '
b10110100 (
#519
0$
#520
1$
b10111000101110011011101010111011 '
b10111000 (
#521
0$
#522
1$
b10111100101111011011111010111111 '
b10111100 (
#523
0$
#524
1$
b11000000110000011100001011000011 '
b11000000 (
#525
0$
#526
1$
b11000100110001011100011011000111 '
b11000100 (
#527
0$
#528
1$
b11001000110010011100101011001011 '
b11001000 (
#529
0$
#530
1$
b11001100110011011100111011001111 '
b11001100 (
#531
0$
#532
1$
b11010000110100011101001011010011 '
b11010000 (
#533
0$
#534
1$
b11010100110101011101011011010111 '
b11010100 (
#535
0$
#536
1$
b11011000110110011101101011011011 '
b11011000 (
#537
0$
#538
1$
b11011100110111011101111011011111 '
b11011100 (
#539
0$
#540
1$
b11100000111000011110001011100011 '
b11100000 (
#541
0$
#542
1$
b11100100111001011110011011100111 '
b11100100 (
#543
0$
#544
1$
b11101000111010011110101011101011 '
b11101000 (
#545
0$
#546
1$
b11101100111011011110111011101111 '
b11101100 (
#547
0$
#548
1$
b11110000111100011111001011110011 '
b11110000 (
#549
0$
#550
1$
b11110100111101011111011011110111 '
b11110100 (
#551
0$
#552
1$
b11111000111110011111101011111011 '
b11111000 (
#553
0$
#554
1$
b11111100111111011111111011111111 '
b11111100 (
#555
0$
#556
1$
b00000000000000010000001000000011 '
b00000000 (
#557
0$
#558
1$
b00000100000001010000011000000111 '
b00000100 (
#559
0$
#560
1$
b00001000000010010000101000001011 '
b00001000 (
#561
0$
#562
1$
b00001100000011010000111000001111 '
b00001100 (
#563
0$
#564
1$
b00010000000100010001001000010011 '
b00010000 (
#565
0$
#566
1$
b00010100000101010001011000010111 '
b00010100 (
#567
0$
#568
1$
b00011000000110010001101000011011 '
b00011000 (
#569
0$
#570
1$
b00011100000111010001111000011111 '
b00011100 (
#571
0$
#572
1$
b00100000001000010010001000100011 '
b00100000 (
#573
0$
#574
1$
b00100100001001010010011000100111 '
b00100100 (
#575
0$
#576
1$
b00101000001010010010101000101011 '
b00101000 (
#577
0$
#578
1$
b00101100001011010010111000101111 '
b00101100 (
#579
0$
#580
1$
b00110000001100010011001000110011 '
b00110000 (
#581
0$
#582
1$
b00110100001101010011011000110111 '
b00110100 (
#583
0$
#584
1$
b00111000001110010011101000111011 '
b00111000 (
#585
0$
#586
1$
b00111100001111010011111000111111 '
b00111100 (
#587
0$
#588
1$
b01000000010000010100001001000011 '
b01000000 (
#589
0$
#590
1$
b01000100010001010100011001000111 '
b01000100 (
#591
0$
#592
1$
b01001000010010010100101001001011 '
b01001000 (
#593
0$
#594
1$
b01001100010011010100111001001111 '
b01001100 (
#595
0$
#596
1$
b01010000010100010101001001010011 '
b01010000 (
#597
0$
#598
1$
b01010100010101010101011001010111 '
b01010100 (
#599
0$
#600
1$
b01011000010110010101101001011011 '
b01011000 (
#601
0$
#602
1$
b01011100010111010101111001011111 '
b01011100 (
#603
0$
#604
1$
b01100000011000010110001001100011 '
b01100000 (
#605
0$
#606
1$
b01100100011001010110011001100111 '
b01100100 (
#607
0$
#608
1$
b01101000011010010110101001101011 '
b01101000 (
#609
0$
#610
1$
b01101100011011010110111001101111 '
b01101100 (
#611
0$
#612
1$
b01110000011100010111001001110011 '
b01110000 (
#613
0$
#614
1$
b01110100011101010111011001110111 '
b01110100 (
#615
0$
#616
1$
b01111000011110010111101001111011 '
b01111000 (
#617
0$
#618
1$
b01111100011111010111111001111111 '
b01111100 (
#619
0$
#620
1$
b10000000100000011000001010000011 '
b10000000 (
#621
0$
#622
1$
b10000100100001011000011010000111 '
b10000100 (
#623
0$
#624
1$
b10001000100010011000101010001011 '
b10001000 (
#625
0$
#626
1$
b10001100100011011000111010001111 '
b10001100 (
#627
0$
#628
1$
b10010000100100011001001010010011 '
b10010000 (
#629
0$
#630
1$
b10010100100101011001011010010111 '
b10010100 (
#631
0$
#632
1$
b10011000100110011001101010011011 '
b10011000 (
#633
0$
#634
1$
b10011100100111011001111010011111 '
b10011100 (
#635
0$
#636
1$
b10100000101000011010001010100011 '
b10100000 (
#637
0$
#638
1$
b10100100101001011010011010100111 '
b10100100 (
#639
0$
#640
1$
b10101000101010011010101010101011 '
b10101000 (
#641
0$
#642
1$
b10101100101011011010111010101111 '
b10101100 (
#643
0$
#644
1$
b10110000101100011011001010110011 '
b10110000 (
#645
0$
#646
1$
b10110100101101011011011010110111 '
b10110100 (
#647
0$
#648
1$
b10111000101110011011101010111011 '
b10111000 (
#649
0$
#650
1$
b10111100101111011011111010111111 '
b10111100 (
#651
0$
#652
1$
b11000000110000011100001011000011 '
b11000000 (
#653
0$
#654
1$
b11000100110001011100011011000111 '
b11000100 (
#655
0$
#656
1$
b11001000110010011100101011001011 '
b11001000 (
#657
0$
#658
1$
b11001100110011011100111011001111 '
b11001100 (
#659
0$
#660
1$
b11010000110100011101001011010011 '
b11010000 (
#661
0$
#662
1$
b11010100110101011101011011010111 '
b11010100 (
#663
0$
#664
1$
b11011000110110011101101011011011 '
b11011000 (
#665
0$
#666
1$
b11011100110111011101111011011111 '
b11011100 (
#667
0$
#668
1$
b11100000111000011110001011100011 '
b11100000 (
#669
0$
#670
1$
b11100100111001011110011011100111 '
b11100100 (
#671
0$
#672
1$
b11101000111010011110101011101011 '
b11101000 (
#673
0$
#674
1$
b11101100111011011110111011101111 '
b11101100 (
#675
0$
#676
1$
b11110000111100011111001011110011 '
b11110000 (
#677
0$
#678
1$
b11110100111101011111011011110111 '
b11110100 (
#679
0$
#680
1$
b11111000111110011111101011111011 '
b11111000 (
#681
0$
#682
1$
b11111100111111011111111011111111 '
b11111100 (
#683
0$
#684
1$
b00000000000000010000001000000011 '
b00000000 (
#685
0$
#686
1$
b00000100000001010000011000000111 '
b00000100 (
#687
0$
#688
1$
b00001000000010010000101000001011 '
b00001000 (
#689
0$
#690
1$
b00001100000011010000111000001111 '
b00001100 (
#691
0$
#692
1$
b00010000000100010001001000010011 '
b00010000 (
#693
0$
#694
1$
b00010100000101010001011000010111 '
b00010100 (
#695
0$
#696
1$
b00011000000110010001101000011011 '
b00011000 (
#697
0$
#698
1$
b00011100000111010001111000011111 '
b00011100 (
#699
0$
#700
1$
b00100000001000010010001000100011 '
b00100000 (
#701
0$
#702
1$
b00100100001001010010011000100111 '
b00100100 (
#703
0$
#704
1$
b00101000001010010010101000101011 '
b00101000 (
#705
0$
#706
1$
b00101100001011010010111000101111 '
b00101100 (
#707
0$
#708
1$
b00110000001100010011001000110011 '
b00110000 (
#709
0$
#710
1$
b00110100001101010011011000110111 '
b00110100 (
#711
0$
#712
1$
b00111000001110010011101000111011 '
b00111000 (
#713
0$
#714
1$
b00111100001111010011111000111111 '
b00111100 (
#715
0$
#716
1$
b01000000010000010100001001000011 '
b01000000 (
#717
0$
#718
1$
b01000100010001010100011001000111 '
b01000100 (
#719
0$
#720
1$
b01001000010010010100101001001011 '
b01001000 (
#721
0$
#722
1$
b01001100010011010100111001001111 '
b01001100 (
#723
0$
#724
1$
b01010000010100010101001001010011 '
b01010000 (
#725
0$
#726
1$
b01010100010101010101011001010111 '
b01010100 (
#727
0$
#728
1$
b01011000010110010101101001011011 '
b01011000 (
#729
0$
#730
1$
b01011100010111010101111001011111 '
b01011100 (
#731
0$
#732
1$
b01100000011000010110001001100011 '
b01100000 (
#733
0$
#734
1$
b01100100011001010110011001100111 '
b01100100 (
#735
0$
#736
1$
b01101000011010010110101001101011 '
b01101000 (
#737
0$
#738
1$
b01101100011011010110111001101111 '
b01101100 (
#739
0$
#740
1$
b01110000011100010111001001110011 '
b01110000 (
#741
0$
#742
1$
b01110100011101010111011001110111 '
b01110100 (
#743
0$
#744
1$
b01111000011110010111101001111011 '
b01111000 (
#745
0$
#746
1$
b01111100011111010111111001111111 '
b01111100 (
#747
0$
#748
1$
b10000000100000011000001010000011 '
b10000000 (
#749
0$
#750
1$
b10000100100001011000011010000111 '
b10000100 (
#751
0$
#752
1$
b10001000100010011000101010001011 '
b10001000 (
#753
0$
#754
1$
b10001100100011011000111010001111 '
b10001100 (
#755
0$
#756
1$
b10010000100100011001001010010011 '
b10010000 (
#757
0$
#758
1$
b10010100100101011001011010010111 '
b10010100 (
#759
0$
#760
1$
b10011000100110011001101010011011 '
b10011000 (
#761
0$
#762
1$
b10011100100111011001111010011111 '
b10011100 (
#763
0$
#764
1$
b10100000101000011010001010100011 '
b10100000 (
#765
0$
#766
1$
b10100100101001011010011010100111 '
b10100100 (
#767
0$
#768
1$
b10101000101010011010101010101011 '
b10101000 (
#769
0$
#770
1$
b10101100101011011010111010101111 '
b10101100 (
#771
0$
#772
1$
b10110000101100011011001010110011 '
b10110000 (
#773
0$
#774
1$
b10110100101101011011011010110111 '
b10110100 (
#775
0$
#776
1$
b10111000101110011011101010111011 '
b10111000 (
#777
0$
#778
1$
b10111100101111011011111010111111 '
b10111100 (
#779
0$
#780
1$
b11000000110000011100001011000011 '
b11000000 (
#781
0$
#782
1$
b11000100110001011100011011000111 '
b11000100 (
#783
0$
#784
1$
b11001000110010011100101011001011 '
b11001000 (
#785
0$
#786
1$
b11001100110011011100111011001111 '
b11001100 (
#787
0$
#788
1$
b11010000110100011101001011010011 '
b11010000 (
#789
0$
#790
1$
b11010100110101011101011011010111 '
b11010100 (
#791
0$
